setup.cfg
setup.py
pip_beacons_sample_python/__init__.py
pip_beacons_sample_python.egg-info/PKG-INFO
pip_beacons_sample_python.egg-info/SOURCES.txt
pip_beacons_sample_python.egg-info/dependency_links.txt
pip_beacons_sample_python.egg-info/requires.txt
pip_beacons_sample_python.egg-info/top_level.txt
pip_beacons_sample_python.egg-info/zip-safe
pip_beacons_sample_python/build/BeaconsClientFactory.py
pip_beacons_sample_python/build/BeaconsServiceFactory.py
pip_beacons_sample_python/build/__init__.py
pip_beacons_sample_python/clients/__init__.py
pip_beacons_sample_python/clients/version1/BeaconsDirectClientV1.py
pip_beacons_sample_python/clients/version1/BeaconsHttpClientV1.py
pip_beacons_sample_python/clients/version1/BeaconsMockClientV1.py
pip_beacons_sample_python/clients/version1/BeaconsNullClientV1.py
pip_beacons_sample_python/clients/version1/IBeaconsClientV1.py
pip_beacons_sample_python/clients/version1/__init__.py
pip_beacons_sample_python/container/BeaconsProcess.py
pip_beacons_sample_python/container/__init__.py
pip_beacons_sample_python/data/__init__.py
pip_beacons_sample_python/data/version1/BeaconTypeV1.py
pip_beacons_sample_python/data/version1/BeaconV1.py
pip_beacons_sample_python/data/version1/BeaconV1Schema.py
pip_beacons_sample_python/data/version1/__init__.py
pip_beacons_sample_python/logic/BeaconsCommandSet.py
pip_beacons_sample_python/logic/BeaconsController.py
pip_beacons_sample_python/logic/IBeaconsController.py
pip_beacons_sample_python/logic/__init__.py
pip_beacons_sample_python/persistence/BeaconsFilePersistence.py
pip_beacons_sample_python/persistence/BeaconsMemoryPersistence.py
pip_beacons_sample_python/persistence/BeaconsMongoDbPersistence.py
pip_beacons_sample_python/persistence/IBeaconsPersistence.py
pip_beacons_sample_python/persistence/__init__.py
pip_beacons_sample_python/services/__init__.py
pip_beacons_sample_python/services/version1/BeaconsHttpServiceV1.py
pip_beacons_sample_python/services/version1/__init__.py
test/clients/__init__.py
test/clients/version1/BeaconsClientV1Fixture.py
test/clients/version1/__init__.py
test/clients/version1/test_BeaconsDirectClientV1.py
test/clients/version1/test_BeaconsHttpClientV1.py
test/clients/version1/test_BeaconsMockClientV1.py
test/logic/__init__.py
